README.md
setup.cfg
setup.py
aioble/__init__.py
aioble/centralmanager.py
aioble/characteristic.py
aioble/descriptor.py
aioble/device.py
aioble/service.py
aioble.egg-info/PKG-INFO
aioble.egg-info/SOURCES.txt
aioble.egg-info/dependency_links.txt
aioble.egg-info/requires.txt
aioble.egg-info/top_level.txt
aioble/bluezdbus/__init__.py
aioble/bluezdbus/centralmanager.py
aioble/bluezdbus/characteristic.py
aioble/bluezdbus/descriptor.py
aioble/bluezdbus/device.py
aioble/bluezdbus/service.py
aioble/corebluetooth/__init__.py
aioble/corebluetooth/centralmanager.py
aioble/corebluetooth/characteristic.py
aioble/corebluetooth/device.py
aioble/corebluetooth/service.py
aioble/corebluetooth/util.py
aioble/dotnet/UWPBluetoothPython.dll
aioble/dotnet/__init__.py
aioble/dotnet/centralmanager.py
aioble/dotnet/characteristic.py
aioble/dotnet/descriptor.py
aioble/dotnet/device.py
aioble/dotnet/service.py
aioble/dotnet/utils.py