Metadata-Version: 1.1
Name: aioble
Version: 0.0.1
Summary: An asynchronous (asyncio) bluetooth low energy (BLE) python library
Home-page: https://github.com/detectlabs/aioble
Author: detect labs
Author-email: code@detectlabs.io
License: UNKNOWN
Download-URL: https://github.com/detectlabs/aioble/archive/v0.0.1.tar.gz
Platform: UNKNOWN
